py_commiter/__init__.py
py_commiter/__main__.py
py_commiter/commit.py
py_commiter/git.py
py_commiter-0.1.0.dist-info/licenses/LICENSE
py_commiter-0.1.0.dist-info/METADATA
py_commiter-0.1.0.dist-info/WHEEL
py_commiter-0.1.0.dist-info/entry_points.txt
py_commiter-0.1.0.dist-info/top_level.txt
py_commiter-0.1.0.dist-info/RECORD
