Metadata-Version: 2.4
Name: py-commiter
Version: 0.1.0
Summary: A CLI tool to create Conventional Commits with emoji and scope selection.
Home-page: https://github.com/MatiasTilleriasLey/py-commiter
Author: Matias Tillerias
Classifier: Programming Language :: Python :: 3
Classifier: License :: OSI Approved :: MIT License
Classifier: Operating System :: OS Independent
Requires-Python: >=3.7
License-File: LICENSE
Requires-Dist: prompt_toolkit
Requires-Dist: tabulate
Dynamic: author
Dynamic: classifier
Dynamic: description
Dynamic: description-content-type
Dynamic: home-page
Dynamic: license-file
Dynamic: requires-dist
Dynamic: requires-python
Dynamic: summary
